cleaner/__init__.py
cleaner/__main__.py
cleaner/commands/__init__.py
cleaner/commands/check.py
cleaner/commands/remove.py
cleaner/config.py
cleaner/searcher.py
cleaner/utils.py
cleaner_py-0.2.1.dist-info/entry_points.txt
cleaner_py-0.2.1.dist-info/WHEEL
cleaner_py-0.2.1.dist-info/METADATA
cleaner_py-0.2.1.dist-info/RECORD
