Metadata-Version: 2.1
Name: cleaner-py
Version: 0.2.1
Summary: Check for virtual environments and packages that you haven't used recently and clean them.
License: MIT
Author: Schumi543
Author-email: 12729148+Schumi543@users.noreply.github.com
Requires-Python: >=3.7,<4.0
Classifier: License :: OSI Approved :: MIT License
Classifier: Programming Language :: Python :: 3
Classifier: Programming Language :: Python :: 3.7
Classifier: Programming Language :: Python :: 3.8
Requires-Dist: cleo (>=0.8.1,<0.9.0)
Requires-Dist: clikit (>=0.6.2,<0.7.0)
Requires-Dist: pyyaml (>=5.3.1,<6.0.0)
